prism_ai/__init__.py
prism_ai/api_resources/api_resource.py
prism_ai/api_resources/knowledge.py
prism_ai/api_resources/knowledge_base.py
prism_ai/api_resources/reply.py
prism_ai-0.1.0.dist-info/LICENSE
prism_ai-0.1.0.dist-info/METADATA
prism_ai-0.1.0.dist-info/WHEEL
prism_ai-0.1.0.dist-info/RECORD
