Metadata-Version: 2.1
Name: prism-ai
Version: 0.1.0
Summary: 
Author: gwhite
Requires-Python: >=3.10,<4.0
Classifier: Programming Language :: Python :: 3
Classifier: Programming Language :: Python :: 3.10
Classifier: Programming Language :: Python :: 3.11
Requires-Dist: httpx (>=0.25.0,<0.26.0)
Requires-Dist: requests (>=2.31.0,<3.0.0)
Requires-Dist: tqdm (>=4.66.1,<5.0.0)
